picasa/__init__.py
picasa/picasa.py
picasa/dutil/__init__.py
picasa/dutil/data.py
picasa/dutil/dataloader.py
picasa/dutil/dataloader_base.py
picasa/dutil/dataloader_latent.py
picasa/dutil/dataloader_pair.py
picasa/model/__init__.py
picasa/model/inference.py
picasa/model/loss.py
picasa/model/picasa_model.py
picasa/model/train.py
picasa/util/__init__.py
picasa/util/approxNN.py
picasa/util/palette.py
picasa/util/plots.py
picasa-0.1.0.dist-info/METADATA
picasa-0.1.0.dist-info/WHEEL
picasa-0.1.0.dist-info/top_level.txt
picasa-0.1.0.dist-info/RECORD
