Metadata-Version: 2.4
Name: picasa
Version: 0.1.0
Summary: PICASA, Partitioning Inter-patient Cellular Attributes by Shared Attention, project python package
Home-page: https://github.com/causalpathlab/picasa
Author: Sishir Subedi and Yongjin Park
Author-email: 
License: MIT
Classifier: Programming Language :: Python :: 3
Classifier: License :: OSI Approved :: MIT License
Classifier: Operating System :: OS Independent
Requires-Python: >=3.6
Requires-Dist: anndata==0.10.8
Requires-Dist: annoy==1.17.0
Requires-Dist: numpy==1.24.4
Requires-Dist: pandas>=2.0.3
Requires-Dist: scanpy==1.9.3
Requires-Dist: torch==2.5.1
Dynamic: author
Dynamic: classifier
Dynamic: description
Dynamic: description-content-type
Dynamic: home-page
Dynamic: license
Dynamic: requires-dist
Dynamic: requires-python
Dynamic: summary
